{
  "games": [
    {
      "name": "PaintWarfare",
      "version": "2.9",
      "download_url": "https://drive.usercontent.google.com/download?id=1tidKal0HL528u391y74bXozcVUIOHMfZ&export=download&authuser=0&confirm=t&uuid=65fd9afb-ba01-491b-b3de-bbd8fd13147a&at=AN8xHoqSmwc_LwXt9q1PlJnSA6x4%3A1751912192349",
      "executable_name": "StandKnife.exe"
    },
    {
      "name": "Rustbound",
      "version": "0.0",
      "download_url": "https://example.com/AnotherGame.zip",
      "executable_name": "rustbound.exe"
    }
  ]
}
